src/__init__.py
src/main.py
src/abis/CSAccounting.json
src/abis/CSFeeDistributor.json
src/abis/CSModule.json
src/abis/WithdrawalQueueERC721.json
src/abis/__init__.py
src/abis/stETH.json
src/cli/__init__.py
src/cli/commands.py
src/core/__init__.py
src/core/config.py
src/core/contracts.py
src/core/types.py
src/data/__init__.py
src/data/beacon.py
src/data/cache.py
src/data/etherscan.py
src/data/ipfs_logs.py
src/data/known_cids.py
src/data/lido_api.py
src/data/onchain.py
src/data/rewards_tree.py
src/data/strikes.py
src/services/__init__.py
src/services/operator_service.py
src/web/__init__.py
src/web/app.py
src/web/routes.py
csm_dashboard-0.3.5.dist-info/METADATA
csm_dashboard-0.3.5.dist-info/WHEEL
csm_dashboard-0.3.5.dist-info/entry_points.txt
csm_dashboard-0.3.5.dist-info/RECORD
