Metadata-Version: 2.4
Name: csm-dashboard
Version: 0.3.5
Summary: Lido CSM Operator Dashboard for tracking validator earnings
Requires-Python: >=3.11
Requires-Dist: fastapi>=0.104
Requires-Dist: httpx>=0.25
Requires-Dist: pydantic-settings>=2.0
Requires-Dist: pydantic>=2.5
Requires-Dist: python-dotenv>=1.0
Requires-Dist: rich>=13.0
Requires-Dist: typer>=0.9
Requires-Dist: uvicorn>=0.24
Requires-Dist: web3>=6.0
Provides-Extra: dev
Requires-Dist: pytest-asyncio>=0.21; extra == 'dev'
Requires-Dist: pytest-httpx>=0.21; extra == 'dev'
Requires-Dist: pytest>=7.0; extra == 'dev'
